<?xml version="1.0"?>
<!--
** DO NOT EDIT THIS FILE.
** If you make changes to this file while any VirtualBox related application
** is running, your changes will be overwritten later, without taking effect.
** Use VBoxManage or the VirtualBox Manager GUI to make changes.
**
** Written by VirtualBox 7.2.4 (r170995)
-->
<VirtualBox xmlns="http://www.virtualbox.org/" version="1.12-linux">
  <Global>
    <ExtraData>
      <ExtraDataItem name="GUI/LastItemSelected" value="m=542419c3-6450-45e8-be2d-8285789d2072"/>
      <ExtraDataItem name="GUI/LastWindowPosition" value="9,76,1902,994"/>
      <ExtraDataItem name="GUI/MaxGuestResolution" value="1920,1080"/>
      <ExtraDataItem name="GUI/RecentFolderCD" value="/home/jono/Downloads"/>
      <ExtraDataItem name="GUI/RecentListCD" value="/home/jono/Downloads/ubuntu-22.04.5-desktop-amd64.iso,/home/jono/Downloads/AmogOS-1.5.0-x86_64.iso,/home/jono/Downloads/Win10_22H2_English_x64v1.iso"/>
      <ExtraDataItem name="GUI/ScaleFactor" value="1.1"/>
      <ExtraDataItem name="GUI/Settings/ExpertMode" value="true"/>
      <ExtraDataItem name="GUI/SuppressMessages" value="showRuntimeError.warning.SerialPortIoError,confirmGoingScale"/>
      <ExtraDataItem name="GUI/Tools/LastItemsSelected" value="Machines,Logs"/>
      <ExtraDataItem name="GUI/VMActivityMonitorDataSeriesColors" value="#ffff00ff,#ff0000ff"/>
      <ExtraDataItem name="GUI/VirtualMediaManager/Details/Expanded" value="true"/>
    </ExtraData>
    <MachineRegistry>
      <MachineEntry uuid="{fdfa87e9-410c-4a50-aabb-3e2a2963af35}" src="/home/jono/VirtualBox VMs/Windows 10/Windows 10.vbox"/>
      <MachineEntry uuid="{542419c3-6450-45e8-be2d-8285789d2072}" src="/home/jono/VirtualBox VMs/Sussy/Sussy.vbox"/>
      <MachineEntry uuid="{81144a6b-c5a4-44c7-8365-f56d2b3d87ae}" src="/home/jono/VirtualBox VMs/Ubuntu 22.04.5 LTS/Ubuntu 22.04.5 LTS.vbox"/>
    </MachineRegistry>
    <NetserviceRegistry>
      <DHCPServers>
        <DHCPServer networkName="HostInterfaceNetworking-vboxnet0" IPAddress="192.168.56.100" networkMask="255.255.255.0" lowerIP="192.168.56.101" upperIP="192.168.56.254" enabled="1"/>
      </DHCPServers>
    </NetserviceRegistry>
    <SharedFolders/>
    <Updates enabled="false">
      <Host enabled="false" channel="1" checkFreqSec="86400" repoUrl="https://update.virtualbox.org" checkCount="0"/>
    </Updates>
    <SystemProperties defaultMachineFolder="/home/jono/VirtualBox VMs" defaultHardDiskFormat="VDI" VRDEAuthLibrary="VBoxAuth" webServiceAuthLibrary="VBoxAuth" LogHistoryCount="3" proxyMode="0" exclusiveHwVirt="true"/>
    <USBDeviceFilters/>
  </Global>
</VirtualBox>
